jpgis_dem-0.0.7.dist-info/licenses/LICENSE
jpgisdem/__init__.py
jpgis_dem-0.0.7.dist-info/METADATA
jpgis_dem-0.0.7.dist-info/WHEEL
jpgis_dem-0.0.7.dist-info/entry_points.txt
jpgis_dem-0.0.7.dist-info/top_level.txt
jpgis_dem-0.0.7.dist-info/RECORD
