Metadata-Version: 2.4
Name: jpgis-dem
Version: 0.0.7
Summary: Convert JPGIS .xml DEM files to geotiffs.
Home-page: https://github.com/gpxz/jpgis-dem
Download-URL: https://github.com/gpxz/jpgis-dem
Author: Andrew Nisbet
Author-email: andrew@gpxz.io
License: The MIT License
Keywords: elevation
Classifier: Intended Audience :: Developers
Classifier: Intended Audience :: Science/Research
Classifier: License :: OSI Approved :: MIT License
Classifier: Natural Language :: English
Classifier: Operating System :: OS Independent
Classifier: Programming Language :: Python :: 3
Classifier: Topic :: Scientific/Engineering :: GIS
License-File: LICENSE
Requires-Dist: click
Requires-Dist: lxml
Requires-Dist: numpy
Requires-Dist: rasterio
Dynamic: author
Dynamic: author-email
Dynamic: classifier
Dynamic: description
Dynamic: description-content-type
Dynamic: download-url
Dynamic: home-page
Dynamic: keywords
Dynamic: license
Dynamic: license-file
Dynamic: requires-dist
Dynamic: summary
